subtask_manager-0.2.1.dist-info/METADATA
subtask_manager-0.2.1.dist-info/WHEEL
subtask_manager-0.2.1.dist-info/entry_points.txt
subtask_manager-0.2.1.dist-info/licenses/LICENSE
subtask_manager/__init__.py
subtask_manager/_core.pyd
subtask_manager/_core.pyi
subtask_manager-0.2.1.dist-info/RECORD
