Metadata-Version: 2.4
Name: subtask-manager
Version: 0.2.1
Requires-Dist: pydantic>=2.11.9
License-File: LICENSE
Summary: ETL Subtask management library written in Rust
Author-email: Din Gior <dingior10@gmail.com>
License: MIT
Requires-Python: >=3.11
